emodels/__init__.py
emodels/config.py
emodels/py.typed
emodels/datasets/__init__.py
emodels/datasets/hugging.py
emodels/datasets/models.py
emodels/datasets/stypes.py
emodels/datasets/tokenizers.py
emodels/datasets/utils.py
emodels/extract/__init__.py
emodels/extract/cluster.py
emodels/extract/spider.py
emodels/extract/table.py
emodels/extract/utils.py
emodels/html2text/__init__.py
emodels/html2text/config.py
emodels/html2text/elements.py
emodels/html2text/typing.py
emodels/html2text/utils.py
emodels/scrapyutils/__init__.py
emodels/scrapyutils/loader.py
emodels/scrapyutils/response.py
e_models-1.12.dist-info/LICENSE
e_models-1.12.dist-info/METADATA
e_models-1.12.dist-info/WHEEL
e_models-1.12.dist-info/top_level.txt
e_models-1.12.dist-info/RECORD
