Metadata-Version: 2.1
Name: e-models
Version: 1.12
Summary: Tools for helping build of extraction models with scrapy spiders.
Home-page: https://github.com/kalessin/emodels
Author: Martin Olveyra
Author-email: molveyra@gmail.com
License: BSD
Classifier: Development Status :: 3 - Alpha
Classifier: Intended Audience :: Developers
Classifier: License :: OSI Approved :: BSD License
Classifier: Operating System :: OS Independent
Classifier: Programming Language :: Python :: 3
License-File: LICENSE
Requires-Dist: scikit-learn
Requires-Dist: scrapy
Requires-Dist: sentencepiece
Requires-Dist: shub-workflow>=1.14.0.2
Provides-Extra: with-transformers
Requires-Dist: datasets; extra == "with-transformers"
Requires-Dist: torch; extra == "with-transformers"
Requires-Dist: transformers[torch]; extra == "with-transformers"
